django_group_user_permissions/__init__.py
django_group_user_permissions/group_user_permissions.py
django_group_user_permissions-0.0.2.dist-info/licenses/LICENSE
django_group_user_permissions-0.0.2.dist-info/METADATA
django_group_user_permissions-0.0.2.dist-info/WHEEL
django_group_user_permissions-0.0.2.dist-info/top_level.txt
django_group_user_permissions-0.0.2.dist-info/RECORD
